
{
"letter": "a",
"version": "1",
"rows": 9,
"cols": 9,
"pixels": [
    [0,0,0,0,1,0,0,0,0],
    [0,0,0,1,1,1,0,0,0],
    [0,0,1,1,0,1,1,0,0],
    [0,0,1,0,0,0,1,0,0],
    [0,1,1,0,0,0,1,1,0],
    [0,1,1,1,1,1,1,1,0],
    [1,1,0,0,0,0,0,1,1],
    [1,1,0,0,0,0,0,1,1],
    [1,1,0,0,0,0,0,1,1]
    ]
}

{
"letter": "a",
"version": "2",
"rows": 9,
"cols": 9,
"pixels": [
    [0,0,0,0,1,0,0,0,0],
    [0,0,0,1,0,1,0,0,0],
    [0,0,1,1,0,1,1,0,0],
    [0,0,1,0,0,0,1,0,0],
    [0,1,1,0,0,0,1,1,0],
    [0,1,1,1,1,1,1,1,0],
    [1,0,0,0,0,0,0,0,1],
    [1,1,0,0,0,0,0,1,1],
    [1,1,0,0,0,0,0,1,1]
    ]
}
{
"letter": "a",
"version": "3",
"rows": 9,
"cols": 9,
"pixels": [
    [0,0,0,0,1,0,0,0,0],
    [0,0,0,1,0,1,0,0,0],
    [0,0,1,1,0,1,1,0,0],
    [0,0,1,0,0,0,1,0,0],
    [0,1,0,0,0,0,0,1,0],
    [0,1,1,1,1,1,1,1,0],
    [1,0,0,0,0,0,0,0,1],
    [1,0,0,0,0,0,0,0,1],
    [1,0,0,0,0,0,0,0,1]
    ]
}
{
"letter": "a",
"version": "4",
"rows": 9,
"cols": 9,
"pixels": [
    [0,0,0,0,1,0,0,0,0],
    [0,0,0,1,0,1,0,0,0],
    [0,0,1,0,0,0,1,0,0],
    [0,0,1,0,0,0,1,0,0],
    [0,1,0,0,0,0,0,1,0],
    [0,1,1,1,1,1,1,1,0],
    [1,1,0,0,0,0,0,1,1],
    [1,1,0,0,0,0,0,1,1],
    [1,1,0,0,0,0,0,1,1]
    ]
}
{
"letter": "b",
"version": "1",
"rows": 9,
"cols": 9,
"pixels": [
    [1,1,1,1,1,1,1,0,0],
    [1,1,1,1,1,1,1,1,0],
    [1,1,0,0,0,0,0,1,1],
    [1,1,0,0,0,0,0,1,0],
    [1,1,1,1,1,1,1,1,0],
    [1,1,0,0,0,0,0,1,0],
    [1,1,0,0,0,0,0,1,1],
    [1,1,1,1,1,1,1,1,0],
    [1,1,1,1,1,1,1,0,0]
    ]
}
{
"letter": "b",
"version": "2",
"rows": 9,
"cols": 9,
"pixels": [
    [1,1,1,1,1,1,1,0,0],
    [1,1,1,1,1,1,1,1,0],
    [1,0,0,0,0,0,0,1,1],
    [1,0,0,0,0,0,0,1,0],
    [1,1,1,1,1,1,1,1,0],
    [1,0,0,0,0,0,0,1,0],
    [1,0,0,0,0,0,0,1,1],
    [1,1,1,1,1,1,1,1,0],
    [1,1,1,1,1,1,1,0,0]
    ]
}
{
"letter": "b",
"version": "3",
"rows": 9,
"cols": 9,
"pixels": [
    [1,1,1,1,1,1,1,0,0],
    [1,1,1,1,1,1,1,1,0],
    [1,0,0,0,0,0,0,1,0],
    [1,0,0,0,0,0,0,1,0],
    [1,1,1,1,1,1,1,1,0],
    [1,0,0,0,0,0,0,1,0],
    [1,0,0,0,0,0,0,1,0],
    [1,1,1,1,1,1,1,1,0],
    [1,1,1,1,1,1,1,0,0]
    ]
}
{
"letter": "b",
"version": "4",
"rows": 9,
"cols": 9,
"pixels": [
    [1,1,1,1,1,1,1,0,0],
    [1,1,1,0,0,0,1,1,0],
    [1,1,0,0,0,0,0,1,1],
    [1,1,0,0,0,0,0,1,0],
    [1,1,1,1,1,1,1,1,0],
    [1,1,0,0,0,0,0,1,0],
    [1,1,0,0,0,0,0,1,1],
    [1,1,0,0,0,0,1,1,0],
    [1,1,1,1,1,1,1,0,0]
    ]
}
{
"letter": "c",
"version": "1",
"rows": 9,
"cols": 9,
"pixels": [
    [0,0,1,1,1,1,1,0,0],
    [0,1,1,0,0,0,1,1,0],
    [1,1,0,0,0,0,0,1,1],
    [1,1,0,0,0,0,0,0,0],
    [1,1,0,0,0,0,0,0,0],
    [1,1,0,0,0,0,0,0,0],
    [1,1,0,0,0,0,0,1,1],
    [0,1,1,0,0,0,1,1,0],
    [0,0,1,1,1,1,1,0,0]
    ]
}
{
"letter": "c",
"version": "2",
"rows": 9,
"cols": 9,
"pixels": [
    [0,0,1,1,1,1,1,0,0],
    [0,1,1,0,0,0,1,1,0],
    [1,0,0,0,0,0,0,1,1],
    [1,0,0,0,0,0,0,0,0],
    [1,0,0,0,0,0,0,0,0],
    [1,0,0,0,0,0,0,0,0],
    [1,0,0,0,0,0,0,1,1],
    [0,1,1,0,0,0,1,1,0],
    [0,0,1,1,1,1,1,0,0]
    ]
}
{
"letter": "c",
"version": "3",
"rows": 9,
"cols": 9,
"pixels": [
    [0,0,1,1,1,1,1,0,0],
    [0,1,1,0,0,0,0,1,0],
    [1,0,0,0,0,0,0,0,1],
    [1,0,0,0,0,0,0,0,0],
    [1,0,0,0,0,0,0,0,0],
    [1,0,0,0,0,0,0,0,0],
    [1,0,0,0,0,0,0,0,1],
    [0,1,1,0,0,0,0,1,0],
    [0,0,1,1,1,1,1,0,0]
    ]
}
{
"letter": "c",
"version": "4",
"rows": 9,
"cols": 9,
"pixels": [
    [0,1,1,1,1,1,1,1,0],
    [0,1,1,0,0,0,1,1,0],
    [1,1,0,0,0,0,0,1,1],
    [1,1,0,0,0,0,0,0,0],
    [1,1,0,0,0,0,0,0,0],
    [1,1,0,0,0,0,0,0,0],
    [1,1,0,0,0,0,0,1,1],
    [0,1,1,0,0,0,1,1,0],
    [0,1,1,1,1,1,1,1,0]
    ]
}
{
"letter": "d",
"version": "1",
"rows": 9,
"cols": 9,
"pixels": [
    [1,1,1,1,1,1,1,0,0],
    [1,1,0,0,0,0,1,1,0],
    [1,1,0,0,0,0,0,1,1],
    [1,1,0,0,0,0,0,1,1],
    [1,1,0,0,0,0,0,1,1],
    [1,1,0,0,0,0,0,1,1],
    [1,1,0,0,0,0,0,1,1],
    [1,1,0,0,0,0,1,1,0],
    [1,1,1,1,1,1,1,0,0]
]
}
{
"letter": "d",
"version": "2",
"rows": 9,
"cols": 9,
"pixels": [
    [1,1,1,1,1,1,1,0,0],
    [1,1,1,1,1,1,1,1,0],
    [1,1,0,0,0,0,0,1,1],
    [1,1,0,0,0,0,0,1,1],
    [1,1,0,0,0,0,0,1,1],
    [1,1,0,0,0,0,0,1,1],
    [1,1,0,0,0,0,0,1,1],
    [1,1,1,1,1,1,1,1,0],
    [1,1,1,1,1,1,1,0,0]
]
}
{
"letter": "d",
"version": "3",
"rows": 9,
"cols": 9,
"pixels": [
    [1,1,1,1,1,1,1,0,0],
    [1,1,0,0,0,0,0,1,0],
    [1,1,0,0,0,0,0,1,1],
    [1,1,0,0,0,0,0,0,1],
    [1,1,0,0,0,0,0,0,1],
    [1,1,0,0,0,0,0,0,1],
    [1,1,0,0,0,0,0,0,1],
    [1,1,0,0,0,0,0,1,0],
    [1,1,1,1,1,1,1,0,0]
]
}
{
"letter": "d",
"version": "4",
"rows": 9,
"cols": 9,
"pixels": [
    [1,1,1,1,1,1,1,0,0],
    [1,0,0,0,0,1,1,1,0],
    [1,0,0,0,0,0,0,1,1],
    [1,0,0,0,0,0,0,0,1],
    [1,0,0,0,0,0,0,0,1],
    [1,0,0,0,0,0,0,0,1],
    [1,0,0,0,0,0,0,1,1],
    [1,0,0,0,0,0,1,1,0],
    [1,1,1,1,1,1,1,0,0]
]
}
